LICENSE
MANIFEST.in
README.rst
setup.py
docs/conf.py
docs/index.rst
docs/modules/configparser.rst
docs/modules/context.rst
docs/modules/router.rst
docs/modules/template.rst
docs/modules/wsgi.rst
potpy/__init__.py
potpy/configparser.py
potpy/context.py
potpy/router.py
potpy/template.py
potpy/util.py
potpy/wsgi.py
potpy.egg-info/PKG-INFO
potpy.egg-info/SOURCES.txt
potpy.egg-info/dependency_links.txt
potpy.egg-info/top_level.txt
potpy/test/__init__.py
potpy/test/test_configparser.py
potpy/test/test_context.py
potpy/test/test_router.py
potpy/test/test_template.py
potpy/test/test_wsgi.py