Metadata-Version: 1.0
Name: potpy
Version: 0.0.1
Summary: A general purpose routing apparatus.
Home-page: https://github.com/dhain/potpy
Author: David Zuwenden
Author-email: dhain@zognot.org
License: MIT
Platform: UNKNOWN
Classifier: Intended Audience :: Developers
Classifier: License :: OSI Approved :: MIT License
Classifier: Programming Language :: Python
Classifier: Topic :: Software Development :: Libraries :: Python Modules
